digi_xbee-1.5.0-py3.12-nspkg.pth
digi/xbee/__init__.py
digi/xbee/ble.py
digi/xbee/comm_interface.py
digi/xbee/devices.py
digi/xbee/exception.py
digi/xbee/filesystem.py
digi/xbee/firmware.py
digi/xbee/io.py
digi/xbee/profile.py
digi/xbee/reader.py
digi/xbee/recovery.py
digi/xbee/sender.py
digi/xbee/serial.py
digi/xbee/xsocket.py
digi/xbee/models/__init__.py
digi/xbee/models/accesspoint.py
digi/xbee/models/address.py
digi/xbee/models/atcomm.py
digi/xbee/models/filesystem.py
digi/xbee/models/hw.py
digi/xbee/models/info.py
digi/xbee/models/message.py
digi/xbee/models/mode.py
digi/xbee/models/options.py
digi/xbee/models/protocol.py
digi/xbee/models/statistics.py
digi/xbee/models/status.py
digi/xbee/models/zdo.py
digi/xbee/packets/__init__.py
digi/xbee/packets/aft.py
digi/xbee/packets/base.py
digi/xbee/packets/bluetooth.py
digi/xbee/packets/cellular.py
digi/xbee/packets/common.py
digi/xbee/packets/devicecloud.py
digi/xbee/packets/digimesh.py
digi/xbee/packets/factory.py
digi/xbee/packets/filesystem.py
digi/xbee/packets/network.py
digi/xbee/packets/raw.py
digi/xbee/packets/relay.py
digi/xbee/packets/socket.py
digi/xbee/packets/wifi.py
digi/xbee/packets/zigbee.py
digi/xbee/util/__init__.py
digi/xbee/util/exportutils.py
digi/xbee/util/srp.py
digi/xbee/util/utils.py
digi/xbee/util/xmodem.py
digi_xbee-1.5.0.dist-info/LICENSE.txt
digi_xbee-1.5.0.dist-info/METADATA
digi_xbee-1.5.0.dist-info/WHEEL
digi_xbee-1.5.0.dist-info/namespace_packages.txt
digi_xbee-1.5.0.dist-info/top_level.txt
digi_xbee-1.5.0.dist-info/RECORD
