Metadata-Version: 2.1
Name: digi-xbee
Version: 1.5.0
Summary: Digi XBee Python library
Home-page: https://github.com/digidotcom/xbee-python
Author: Digi International Inc.
Author-email: tech.support@digi.com
License: Mozilla Public License 2.0 (MPL 2.0)
Project-URL: Documentation, https://xbplib.readthedocs.io
Project-URL: Source, https://github.com/digidotcom/xbee-python
Project-URL: Tracker, https://github.com/digidotcom/xbee-python/issues
Project-URL: Changelog, https://github.com/digidotcom/xbee-python/blob/1.5.0/CHANGELOG.rst
Keywords: xbee,IOT,wireless,radio frequency
Classifier: Development Status :: 5 - Production/Stable
Classifier: Intended Audience :: Developers
Classifier: Intended Audience :: Education
Classifier: Intended Audience :: End Users/Desktop
Classifier: Intended Audience :: Telecommunications Industry
Classifier: Topic :: Software Development :: Libraries
Classifier: Topic :: Software Development :: Libraries :: Python Modules
Classifier: Topic :: Home Automation
Classifier: Topic :: Games/Entertainment
Classifier: License :: OSI Approved :: Mozilla Public License 2.0 (MPL 2.0)
Classifier: Programming Language :: Python
Classifier: Programming Language :: Python :: 3
Classifier: Programming Language :: Python :: 3.6
Classifier: Programming Language :: Python :: 3.7
Classifier: Programming Language :: Python :: 3.8
Classifier: Programming Language :: Python :: 3.9
Classifier: Programming Language :: Python :: 3.10
Classifier: Programming Language :: Python :: 3.11
Classifier: Programming Language :: Python :: 3.12
Classifier: Operating System :: OS Independent
Requires-Python: >=3, !=3.0.*, !=3.1.*, !=3.2.*, !=3.3.*, !=3.4.*, !=3.5.*
License-File: LICENSE.txt
Requires-Dist: pyserial>=3
